[
  {
    "seedLabel": "computer",
    "seedLabel__type": "literal",
    "seedLabel__lang": "en",
    "seed": "http://www.wikidata.org/entity/Q68",
    "seed__type": "uri",
    "related": "http://www.wikidata.org/entity/Q104864977",
    "related__type": "uri",
    "relation": "instance of",
    "relation__type": "literal",
    "relatedLabel": "CID-201",
    "relatedLabel__type": "literal",
    "relatedLabel__lang": "en"
  },
  {
    "seedLabel": "computer",
    "seedLabel__type": "literal",
    "seedLabel__lang": "en",
    "seed": "http://www.wikidata.org/entity/Q68",
    "seed__type": "uri",
    "related": "http://www.wikidata.org/entity/Q99356246",
    "related__type": "uri",
    "relation": "instance of",
    "relation__type": "literal",
    "relatedLabel": "Apple One",
    "relatedLabel__type": "literal",
    "relatedLabel__lang": "en"
  },
  {
    "seedLabel": "computer",
    "seedLabel__type": "literal",
    "seedLabel__lang": "en",
    "seed": "http://www.wikidata.org/entity/Q68",
    "seed__type": "uri",
    "related": "http://www.wikidata.org/entity/Q122600977",
    "related__type": "uri",
    "relation": "instance of",
    "relation__type": "literal",
    "relatedLabel": "Q122600977",
    "relatedLabel__type": "literal"
  },
  {
    "seedLabel": "computer",
    "seedLabel__type": "literal",
    "seedLabel__lang": "en",
    "seed": "http://www.wikidata.org/entity/Q68",
    "seed__type": "uri",
    "related": "http://www.wikidata.org/entity/Q122601145",
    "related__type": "uri",
    "relation": "instance of",
    "relation__type": "literal",
    "relatedLabel": "Q122601145",
    "relatedLabel__type": "literal"
  },
  {
    "seedLabel": "computer",
    "seedLabel__type": "literal",
    "seedLabel__lang": "en",
    "seed": "http://www.wikidata.org/entity/Q68",
    "seed__type": "uri",
    "related": "http://www.wikidata.org/entity/Q122601244",
    "related__type": "uri",
    "relation": "instance of",
    "relation__type": "literal",
    "relatedLabel": "Q122601244",
    "relatedLabel__type": "literal"
  },
  {
    "seedLabel": "computer",
    "seedLabel__type": "literal",
    "seedLabel__lang": "en",
    "seed": "http://www.wikidata.org/entity/Q68",
    "seed__type": "uri",
    "related": "http://www.wikidata.org/entity/Q122601314",
    "related__type": "uri",
    "relation": "instance of",
    "relation__type": "literal",
    "relatedLabel": "Q122601314",
    "relatedLabel__type": "literal"
  },
  {
    "seedLabel": "computer",
    "seedLabel__type": "literal",
    "seedLabel__lang": "en",
    "seed": "http://www.wikidata.org/entity/Q68",
    "seed__type": "uri",
    "related": "http://www.wikidata.org/entity/Q122601859",
    "related__type": "uri",
    "relation": "instance of",
    "relation__type": "literal",
    "relatedLabel": "Q122601859",
    "relatedLabel__type": "literal"
  },
  {
    "seedLabel": "laptop",
    "seedLabel__type": "literal",
    "seedLabel__lang": "en",
    "seed": "http://www.wikidata.org/entity/Q3962",
    "seed__type": "uri",
    "related": "http://www.wikidata.org/entity/Q3926523",
    "related__type": "uri",
    "relation": "instance of",
    "relation__type": "literal",
    "relatedLabel": "Toshiba Qosmio",
    "relatedLabel__type": "literal",
    "relatedLabel__lang": "ru"
  },
  {
    "seedLabel": "computer",
    "seedLabel__type": "literal",
    "seedLabel__lang": "en",
    "seed": "http://www.wikidata.org/entity/Q68",
    "seed__type": "uri",
    "related": "http://www.wikidata.org/entity/Q123945709",
    "related__type": "uri",
    "relation": "instance of",
    "relation__type": "literal",
    "relatedLabel": "Терминал для самостоятельного заказа",
    "relatedLabel__type": "literal",
    "relatedLabel__lang": "ru"
  },
  {
    "seedLabel": "computer",
    "seedLabel__type": "literal",
    "seedLabel__lang": "en",
    "seed": "http://www.wikidata.org/entity/Q68",
    "seed__type": "uri",
    "related": "http://www.wikidata.org/entity/Q131762278",
    "related__type": "uri",
    "relation": "instance of",
    "relation__type": "literal",
    "relatedLabel": "Q131762278",
    "relatedLabel__type": "literal"
  },
  {
    "seedLabel": "computer",
    "seedLabel__type": "literal",
    "seedLabel__lang": "en",
    "seed": "http://www.wikidata.org/entity/Q68",
    "seed__type": "uri",
    "related": "http://www.wikidata.org/entity/Q17770417",
    "related__type": "uri",
    "relation": "instance of",
    "relation__type": "literal",
    "relatedLabel": "FREDERIC",
    "relatedLabel__type": "literal",
    "relatedLabel__lang": "en"
  },
  {
    "seedLabel": "computer",
    "seedLabel__type": "literal",
    "seedLabel__lang": "en",
    "seed": "http://www.wikidata.org/entity/Q68",
    "seed__type": "uri",
    "related": "http://www.wikidata.org/entity/Q134498537",
    "related__type": "uri",
    "relation": "instance of",
    "relation__type": "literal",
    "relatedLabel": "ER 56",
    "relatedLabel__type": "literal",
    "relatedLabel__lang": "en"
  },
  {
    "seedLabel": "computer",
    "seedLabel__type": "literal",
    "seedLabel__lang": "en",
    "seed": "http://www.wikidata.org/entity/Q68",
    "seed__type": "uri",
    "related": "http://www.wikidata.org/entity/Q21654815",
    "related__type": "uri",
    "relation": "instance of",
    "relation__type": "literal",
    "relatedLabel": "Олимпик",
    "relatedLabel__type": "literal",
    "relatedLabel__lang": "ru"
  },
  {
    "seedLabel": "computer",
    "seedLabel__type": "literal",
    "seedLabel__lang": "en",
    "seed": "http://www.wikidata.org/entity/Q68",
    "seed__type": "uri",
    "related": "http://www.wikidata.org/entity/Q97166814",
    "related__type": "uri",
    "relation": "instance of",
    "relation__type": "literal",
    "relatedLabel": "Mansfeld MPC",
    "relatedLabel__type": "literal",
    "relatedLabel__lang": "en"
  },
  {
    "seedLabel": "computer",
    "seedLabel__type": "literal",
    "seedLabel__lang": "en",
    "seed": "http://www.wikidata.org/entity/Q68",
    "seed__type": "uri",
    "related": "http://www.wikidata.org/entity/Q25209376",
    "related__type": "uri",
    "relation": "instance of",
    "relation__type": "literal",
    "relatedLabel": "VUK",
    "relatedLabel__type": "literal",
    "relatedLabel__lang": "en"
  },
  {
    "seedLabel": "laptop",
    "seedLabel__type": "literal",
    "seedLabel__lang": "en",
    "seed": "http://www.wikidata.org/entity/Q3962",
    "seed__type": "uri",
    "related": "http://www.wikidata.org/entity/Q5155578",
    "related__type": "uri",
    "relation": "instance of",
    "relation__type": "literal",
    "relatedLabel": "Compaq Contura",
    "relatedLabel__type": "literal",
    "relatedLabel__lang": "en"
  },
  {
    "seedLabel": "computer",
    "seedLabel__type": "literal",
    "seedLabel__lang": "en",
    "seed": "http://www.wikidata.org/entity/Q68",
    "seed__type": "uri",
    "related": "http://www.wikidata.org/entity/Q65697911",
    "related__type": "uri",
    "relation": "instance of",
    "relation__type": "literal",
    "relatedLabel": "G3",
    "relatedLabel__type": "literal",
    "relatedLabel__lang": "en"
  },
  {
    "seedLabel": "computer",
    "seedLabel__type": "literal",
    "seedLabel__lang": "en",
    "seed": "http://www.wikidata.org/entity/Q68",
    "seed__type": "uri",
    "related": "http://www.wikidata.org/entity/Q20430779",
    "related__type": "uri",
    "relation": "instance of",
    "relation__type": "literal",
    "relatedLabel": "CET 500",
    "relatedLabel__type": "literal",
    "relatedLabel__lang": "ru"
  },
  {
    "seedLabel": "computer",
    "seedLabel__type": "literal",
    "seedLabel__lang": "en",
    "seed": "http://www.wikidata.org/entity/Q68",
    "seed__type": "uri",
    "related": "http://www.wikidata.org/entity/Q17993355",
    "related__type": "uri",
    "relation": "instance of",
    "relation__type": "literal",
    "relatedLabel": "Amstrad Sinclair ZX Spectrum",
    "relatedLabel__type": "literal",
    "relatedLabel__lang": "en"
  },
  {
    "seedLabel": "computer",
    "seedLabel__type": "literal",
    "seedLabel__lang": "en",
    "seed": "http://www.wikidata.org/entity/Q68",
    "seed__type": "uri",
    "related": "http://www.wikidata.org/entity/Q127687940",
    "related__type": "uri",
    "relation": "instance of",
    "relation__type": "literal",
    "relatedLabel": "IBM PS/2 Model 50",
    "relatedLabel__type": "literal",
    "relatedLabel__lang": "en"
  },
  {
    "seedLabel": "computer",
    "seedLabel__type": "literal",
    "seedLabel__lang": "en",
    "seed": "http://www.wikidata.org/entity/Q68",
    "seed__type": "uri",
    "related": "http://www.wikidata.org/entity/Q16082924",
    "related__type": "uri",
    "relation": "instance of",
    "relation__type": "literal",
    "relatedLabel": "Q16082924",
    "relatedLabel__type": "literal"
  },
  {
    "seedLabel": "computer",
    "seedLabel__type": "literal",
    "seedLabel__lang": "en",
    "seed": "http://www.wikidata.org/entity/Q68",
    "seed__type": "uri",
    "related": "http://www.wikidata.org/entity/Q47530327",
    "related__type": "uri",
    "relation": "instance of",
    "relation__type": "literal",
    "relatedLabel": "Types of computers",
    "relatedLabel__type": "literal",
    "relatedLabel__lang": "en"
  },
  {
    "seedLabel": "computer",
    "seedLabel__type": "literal",
    "seedLabel__lang": "en",
    "seed": "http://www.wikidata.org/entity/Q68",
    "seed__type": "uri",
    "related": "http://www.wikidata.org/entity/Q46998793",
    "related__type": "uri",
    "relation": "instance of",
    "relation__type": "literal",
    "relatedLabel": "DP100",
    "relatedLabel__type": "literal",
    "relatedLabel__lang": "en"
  },
  {
    "seedLabel": "computer",
    "seedLabel__type": "literal",
    "seedLabel__lang": "en",
    "seed": "http://www.wikidata.org/entity/Q68",
    "seed__type": "uri",
    "related": "http://www.wikidata.org/entity/Q131611425",
    "related__type": "uri",
    "relation": "instance of",
    "relation__type": "literal",
    "relatedLabel": "Nerdminer",
    "relatedLabel__type": "literal",
    "relatedLabel__lang": "en"
  },
  {
    "seedLabel": "computer",
    "seedLabel__type": "literal",
    "seedLabel__lang": "en",
    "seed": "http://www.wikidata.org/entity/Q68",
    "seed__type": "uri",
    "related": "http://www.wikidata.org/entity/Q102071241",
    "related__type": "uri",
    "relation": "instance of",
    "relation__type": "literal",
    "relatedLabel": "ZX Nucleon 512K",
    "relatedLabel__type": "literal",
    "relatedLabel__lang": "en"
  },
  {
    "seedLabel": "computer",
    "seedLabel__type": "literal",
    "seedLabel__lang": "en",
    "seed": "http://www.wikidata.org/entity/Q68",
    "seed__type": "uri",
    "related": "http://www.wikidata.org/entity/Q123495478",
    "related__type": "uri",
    "relation": "instance of",
    "relation__type": "literal",
    "relatedLabel": "Q123495478",
    "relatedLabel__type": "literal"
  },
  {
    "seedLabel": "computer",
    "seedLabel__type": "literal",
    "seedLabel__lang": "en",
    "seed": "http://www.wikidata.org/entity/Q68",
    "seed__type": "uri",
    "related": "http://www.wikidata.org/entity/Q131674302",
    "related__type": "uri",
    "relation": "instance of",
    "relation__type": "literal",
    "relatedLabel": "Commodore 64 in the Museo della Scienza e della Tecnologia \"Leonardo da Vinci\"",
    "relatedLabel__type": "literal",
    "relatedLabel__lang": "en"
  },
  {
    "seedLabel": "computer",
    "seedLabel__type": "literal",
    "seedLabel__lang": "en",
    "seed": "http://www.wikidata.org/entity/Q68",
    "seed__type": "uri",
    "related": "http://www.wikidata.org/entity/Q131748782",
    "related__type": "uri",
    "relation": "instance of",
    "relation__type": "literal",
    "relatedLabel": "Sinclair ZX Spectrum in Museo scienza tecnologia Milano",
    "relatedLabel__type": "literal",
    "relatedLabel__lang": "en"
  },
  {
    "seedLabel": "computer",
    "seedLabel__type": "literal",
    "seedLabel__lang": "en",
    "seed": "http://www.wikidata.org/entity/Q68",
    "seed__type": "uri",
    "related": "http://www.wikidata.org/entity/Q52152799",
    "related__type": "uri",
    "relation": "instance of",
    "relation__type": "literal",
    "relatedLabel": "Q52152799",
    "relatedLabel__type": "literal"
  },
  {
    "seedLabel": "laptop",
    "seedLabel__type": "literal",
    "seedLabel__lang": "en",
    "seed": "http://www.wikidata.org/entity/Q3962",
    "seed__type": "uri",
    "related": "http://www.wikidata.org/entity/Q3400854",
    "related__type": "uri",
    "relation": "instance of",
    "relation__type": "literal",
    "relatedLabel": "PowerBook 190, PowerBook 190cs",
    "relatedLabel__type": "literal",
    "relatedLabel__lang": "en"
  },
  {
    "seedLabel": "laptop",
    "seedLabel__type": "literal",
    "seedLabel__lang": "en",
    "seed": "http://www.wikidata.org/entity/Q3962",
    "seed__type": "uri",
    "related": "http://www.wikidata.org/entity/Q3400857",
    "related__type": "uri",
    "relation": "instance of",
    "relation__type": "literal",
    "relatedLabel": "PowerBook 520c",
    "relatedLabel__type": "literal",
    "relatedLabel__lang": "en"
  },
  {
    "seedLabel": "computer",
    "seedLabel__type": "literal",
    "seedLabel__lang": "en",
    "seed": "http://www.wikidata.org/entity/Q68",
    "seed__type": "uri",
    "related": "http://www.wikidata.org/entity/Q108060211",
    "related__type": "uri",
    "relation": "instance of",
    "relation__type": "literal",
    "relatedLabel": "SOLO",
    "relatedLabel__type": "literal",
    "relatedLabel__lang": "en"
  },
  {
    "seedLabel": "computer",
    "seedLabel__type": "literal",
    "seedLabel__lang": "en",
    "seed": "http://www.wikidata.org/entity/Q68",
    "seed__type": "uri",
    "related": "http://www.wikidata.org/entity/Q54841571",
    "related__type": "uri",
    "relation": "instance of",
    "relation__type": "literal",
    "relatedLabel": "CAB 500 computer - CnAM 22358",
    "relatedLabel__type": "literal",
    "relatedLabel__lang": "en"
  },
  {
    "seedLabel": "computer",
    "seedLabel__type": "literal",
    "seedLabel__lang": "en",
    "seed": "http://www.wikidata.org/entity/Q68",
    "seed__type": "uri",
    "related": "http://www.wikidata.org/entity/Q123915796",
    "related__type": "uri",
    "relation": "instance of",
    "relation__type": "literal",
    "relatedLabel": "Q123915796",
    "relatedLabel__type": "literal"
  },
  {
    "seedLabel": "computer",
    "seedLabel__type": "literal",
    "seedLabel__lang": "en",
    "seed": "http://www.wikidata.org/entity/Q68",
    "seed__type": "uri",
    "related": "http://www.wikidata.org/entity/Q23831218",
    "related__type": "uri",
    "relation": "instance of",
    "relation__type": "literal",
    "relatedLabel": "Diagram",
    "relatedLabel__type": "literal",
    "relatedLabel__lang": "en"
  },
  {
    "seedLabel": "computer",
    "seedLabel__type": "literal",
    "seedLabel__lang": "en",
    "seed": "http://www.wikidata.org/entity/Q68",
    "seed__type": "uri",
    "related": "http://www.wikidata.org/entity/Q16081611",
    "related__type": "uri",
    "relation": "instance of",
    "relation__type": "literal",
    "relatedLabel": "SMT Goupil 3",
    "relatedLabel__type": "literal",
    "relatedLabel__lang": "en"
  },
  {
    "seedLabel": "computer",
    "seedLabel__type": "literal",
    "seedLabel__lang": "en",
    "seed": "http://www.wikidata.org/entity/Q68",
    "seed__type": "uri",
    "related": "http://www.wikidata.org/entity/Q16114013",
    "related__type": "uri",
    "relation": "instance of",
    "relation__type": "literal",
    "relatedLabel": "TRS-716",
    "relatedLabel__type": "literal",
    "relatedLabel__lang": "en"
  },
  {
    "seedLabel": "computer",
    "seedLabel__type": "literal",
    "seedLabel__lang": "en",
    "seed": "http://www.wikidata.org/entity/Q68",
    "seed__type": "uri",
    "related": "http://www.wikidata.org/entity/Q16114028",
    "related__type": "uri",
    "relation": "instance of",
    "relation__type": "literal",
    "relatedLabel": "TRS 713",
    "relatedLabel__type": "literal",
    "relatedLabel__lang": "en"
  },
  {
    "seedLabel": "computer",
    "seedLabel__type": "literal",
    "seedLabel__lang": "en",
    "seed": "http://www.wikidata.org/entity/Q68",
    "seed__type": "uri",
    "related": "http://www.wikidata.org/entity/Q128601702",
    "related__type": "uri",
    "relation": "instance of",
    "relation__type": "literal",
    "relatedLabel": "IBM PS/2 Model 60",
    "relatedLabel__type": "literal",
    "relatedLabel__lang": "en"
  },
  {
    "seedLabel": "computer",
    "seedLabel__type": "literal",
    "seedLabel__lang": "en",
    "seed": "http://www.wikidata.org/entity/Q68",
    "seed__type": "uri",
    "related": "http://www.wikidata.org/entity/Q128602453",
    "related__type": "uri",
    "relation": "instance of",
    "relation__type": "literal",
    "relatedLabel": "IBM PS/2 Model 80",
    "relatedLabel__type": "literal",
    "relatedLabel__lang": "en"
  },
  {
    "seedLabel": "computer",
    "seedLabel__type": "literal",
    "seedLabel__lang": "en",
    "seed": "http://www.wikidata.org/entity/Q68",
    "seed__type": "uri",
    "related": "http://www.wikidata.org/entity/Q133306487",
    "related__type": "uri",
    "relation": "instance of",
    "relation__type": "literal",
    "relatedLabel": "Q133306487",
    "relatedLabel__type": "literal"
  },
  {
    "seedLabel": "computer",
    "seedLabel__type": "literal",
    "seedLabel__lang": "en",
    "seed": "http://www.wikidata.org/entity/Q68",
    "seed__type": "uri",
    "related": "http://www.wikidata.org/entity/Q106511763",
    "related__type": "uri",
    "relation": "instance of",
    "relation__type": "literal",
    "relatedLabel": "Q106511763",
    "relatedLabel__type": "literal"
  },
  {
    "seedLabel": "computer",
    "seedLabel__type": "literal",
    "seedLabel__lang": "en",
    "seed": "http://www.wikidata.org/entity/Q68",
    "seed__type": "uri",
    "related": "http://www.wikidata.org/entity/Q136705862",
    "related__type": "uri",
    "relation": "instance of",
    "relation__type": "literal",
    "relatedLabel": "Wegematic 1000",
    "relatedLabel__type": "literal",
    "relatedLabel__lang": "en"
  },
  {
    "seedLabel": "computer",
    "seedLabel__type": "literal",
    "seedLabel__lang": "en",
    "seed": "http://www.wikidata.org/entity/Q68",
    "seed__type": "uri",
    "related": "http://www.wikidata.org/entity/Q124418353",
    "related__type": "uri",
    "relation": "instance of",
    "relation__type": "literal",
    "relatedLabel": "Q124418353",
    "relatedLabel__type": "literal"
  },
  {
    "seedLabel": "computer",
    "seedLabel__type": "literal",
    "seedLabel__lang": "en",
    "seed": "http://www.wikidata.org/entity/Q68",
    "seed__type": "uri",
    "related": "http://www.wikidata.org/entity/Q128904411",
    "related__type": "uri",
    "relation": "instance of",
    "relation__type": "literal",
    "relatedLabel": "Q128904411",
    "relatedLabel__type": "literal"
  },
  {
    "seedLabel": "computer",
    "seedLabel__type": "literal",
    "seedLabel__lang": "en",
    "seed": "http://www.wikidata.org/entity/Q68",
    "seed__type": "uri",
    "related": "http://www.wikidata.org/entity/Q19203304",
    "related__type": "uri",
    "relation": "instance of",
    "relation__type": "literal",
    "relatedLabel": "Z25",
    "relatedLabel__type": "literal",
    "relatedLabel__lang": "en"
  },
  {
    "seedLabel": "computer",
    "seedLabel__type": "literal",
    "seedLabel__lang": "en",
    "seed": "http://www.wikidata.org/entity/Q68",
    "seed__type": "uri",
    "related": "http://www.wikidata.org/entity/Q128720282",
    "related__type": "uri",
    "relation": "instance of",
    "relation__type": "literal",
    "relatedLabel": "IBM PS/2 Model 70",
    "relatedLabel__type": "literal",
    "relatedLabel__lang": "en"
  },
  {
    "seedLabel": "laptop",
    "seedLabel__type": "literal",
    "seedLabel__lang": "en",
    "seed": "http://www.wikidata.org/entity/Q3962",
    "seed__type": "uri",
    "related": "http://www.wikidata.org/entity/Q3400853",
    "related__type": "uri",
    "relation": "instance of",
    "relation__type": "literal",
    "relatedLabel": "Q3400853",
    "relatedLabel__type": "literal"
  },
  {
    "seedLabel": "computer",
    "seedLabel__type": "literal",
    "seedLabel__lang": "en",
    "seed": "http://www.wikidata.org/entity/Q68",
    "seed__type": "uri",
    "related": "http://www.wikidata.org/entity/Q128790424",
    "related__type": "uri",
    "relation": "instance of",
    "relation__type": "literal",
    "relatedLabel": "IBM PS/2 Model 55 SX",
    "relatedLabel__type": "literal",
    "relatedLabel__lang": "en"
  },
  {
    "seedLabel": "laptop",
    "seedLabel__type": "literal",
    "seedLabel__lang": "en",
    "seed": "http://www.wikidata.org/entity/Q3962",
    "seed__type": "uri",
    "related": "http://www.wikidata.org/entity/Q189611",
    "related__type": "uri",
    "relation": "instance of",
    "relation__type": "literal",
    "relatedLabel": "Zenith Minisport",
    "relatedLabel__type": "literal",
    "relatedLabel__lang": "en"
  },
  {
    "seedLabel": "computer",
    "seedLabel__type": "literal",
    "seedLabel__lang": "en",
    "seed": "http://www.wikidata.org/entity/Q68",
    "seed__type": "uri",
    "related": "http://www.wikidata.org/entity/Q118609774",
    "related__type": "uri",
    "relation": "instance of",
    "relation__type": "literal",
    "relatedLabel": "Zuse Z22",
    "relatedLabel__type": "literal",
    "relatedLabel__lang": "en"
  },
  {
    "seedLabel": "computer",
    "seedLabel__type": "literal",
    "seedLabel__lang": "en",
    "seed": "http://www.wikidata.org/entity/Q68",
    "seed__type": "uri",
    "related": "http://www.wikidata.org/entity/Q18745907",
    "related__type": "uri",
    "relation": "instance of",
    "relation__type": "literal",
    "relatedLabel": "EPOS",
    "relatedLabel__type": "literal",
    "relatedLabel__lang": "ru"
  },
  {
    "seedLabel": "computer",
    "seedLabel__type": "literal",
    "seedLabel__lang": "en",
    "seed": "http://www.wikidata.org/entity/Q68",
    "seed__type": "uri",
    "related": "http://www.wikidata.org/entity/Q132560637",
    "related__type": "uri",
    "relation": "instance of",
    "relation__type": "literal",
    "relatedLabel": "Majorana 1",
    "relatedLabel__type": "literal",
    "relatedLabel__lang": "ru"
  },
  {
    "seedLabel": "computer",
    "seedLabel__type": "literal",
    "seedLabel__lang": "en",
    "seed": "http://www.wikidata.org/entity/Q68",
    "seed__type": "uri",
    "related": "http://www.wikidata.org/entity/Q83981577",
    "related__type": "uri",
    "relation": "instance of",
    "relation__type": "literal",
    "relatedLabel": "Gepard computer",
    "relatedLabel__type": "literal",
    "relatedLabel__lang": "en"
  },
  {
    "seedLabel": "computer",
    "seedLabel__type": "literal",
    "seedLabel__lang": "en",
    "seed": "http://www.wikidata.org/entity/Q68",
    "seed__type": "uri",
    "related": "http://www.wikidata.org/entity/Q80061396",
    "related__type": "uri",
    "relation": "instance of",
    "relation__type": "literal",
    "relatedLabel": "Q80061396",
    "relatedLabel__type": "literal"
  },
  {
    "seedLabel": "computer",
    "seedLabel__type": "literal",
    "seedLabel__lang": "en",
    "seed": "http://www.wikidata.org/entity/Q68",
    "seed__type": "uri",
    "related": "http://www.wikidata.org/entity/Q118754402",
    "related__type": "uri",
    "relation": "instance of",
    "relation__type": "literal",
    "relatedLabel": "Butale infotech",
    "relatedLabel__type": "literal",
    "relatedLabel__lang": "en"
  },
  {
    "seedLabel": "computer",
    "seedLabel__type": "literal",
    "seedLabel__lang": "en",
    "seed": "http://www.wikidata.org/entity/Q68",
    "seed__type": "uri",
    "related": "http://www.wikidata.org/entity/Q55442718",
    "related__type": "uri",
    "relation": "instance of",
    "relation__type": "literal",
    "relatedLabel": "E-Ball Technology",
    "relatedLabel__type": "literal",
    "relatedLabel__lang": "en"
  },
  {
    "seedLabel": "computer",
    "seedLabel__type": "literal",
    "seedLabel__lang": "en",
    "seed": "http://www.wikidata.org/entity/Q68",
    "seed__type": "uri",
    "related": "http://www.wikidata.org/entity/Q111488100",
    "related__type": "uri",
    "relation": "instance of",
    "relation__type": "literal",
    "relatedLabel": "Q111488100",
    "relatedLabel__type": "literal"
  },
  {
    "seedLabel": "computer",
    "seedLabel__type": "literal",
    "seedLabel__lang": "en",
    "seed": "http://www.wikidata.org/entity/Q68",
    "seed__type": "uri",
    "related": "http://www.wikidata.org/entity/Q138505191",
    "related__type": "uri",
    "relation": "instance of",
    "relation__type": "literal",
    "relatedLabel": "Q138505191",
    "relatedLabel__type": "literal"
  },
  {
    "seedLabel": "computer",
    "seedLabel__type": "literal",
    "seedLabel__lang": "en",
    "seed": "http://www.wikidata.org/entity/Q68",
    "seed__type": "uri",
    "related": "http://www.wikidata.org/entity/Q118976188",
    "related__type": "uri",
    "relation": "instance of",
    "relation__type": "literal",
    "relatedLabel": "IGR learning center at Bayero University Kano state",
    "relatedLabel__type": "literal",
    "relatedLabel__lang": "en"
  },
  {
    "seedLabel": "computer",
    "seedLabel__type": "literal",
    "seedLabel__lang": "en",
    "seed": "http://www.wikidata.org/entity/Q68",
    "seed__type": "uri",
    "related": "http://www.wikidata.org/entity/Q116056735",
    "related__type": "uri",
    "relation": "instance of",
    "relation__type": "literal",
    "relatedLabel": "The Machine",
    "relatedLabel__type": "literal",
    "relatedLabel__lang": "en"
  },
  {
    "seedLabel": "computer",
    "seedLabel__type": "literal",
    "seedLabel__lang": "en",
    "seed": "http://www.wikidata.org/entity/Q68",
    "seed__type": "uri",
    "related": "http://www.wikidata.org/entity/Q20182750",
    "related__type": "uri",
    "relation": "instance of",
    "relation__type": "literal",
    "relatedLabel": "Cobold",
    "relatedLabel__type": "literal",
    "relatedLabel__lang": "en"
  },
  {
    "seedLabel": "computer",
    "seedLabel__type": "literal",
    "seedLabel__lang": "en",
    "seed": "http://www.wikidata.org/entity/Q68",
    "seed__type": "uri",
    "related": "http://www.wikidata.org/entity/Q112628425",
    "related__type": "uri",
    "relation": "instance of",
    "relation__type": "literal",
    "relatedLabel": "MicroOffice RoadRunner",
    "relatedLabel__type": "literal",
    "relatedLabel__lang": "en"
  },
  {
    "seedLabel": "computer",
    "seedLabel__type": "literal",
    "seedLabel__lang": "en",
    "seed": "http://www.wikidata.org/entity/Q68",
    "seed__type": "uri",
    "related": "http://www.wikidata.org/entity/Q122601422",
    "related__type": "uri",
    "relation": "instance of",
    "relation__type": "literal",
    "relatedLabel": "EC 1025",
    "relatedLabel__type": "literal",
    "relatedLabel__lang": "en"
  },
  {
    "seedLabel": "computer",
    "seedLabel__type": "literal",
    "seedLabel__lang": "en",
    "seed": "http://www.wikidata.org/entity/Q68",
    "seed__type": "uri",
    "related": "http://www.wikidata.org/entity/Q122601169",
    "related__type": "uri",
    "relation": "instance of",
    "relation__type": "literal",
    "relatedLabel": "Tesla 200",
    "relatedLabel__type": "literal",
    "relatedLabel__lang": "en"
  },
  {
    "seedLabel": "computer",
    "seedLabel__type": "literal",
    "seedLabel__lang": "en",
    "seed": "http://www.wikidata.org/entity/Q68",
    "seed__type": "uri",
    "related": "http://www.wikidata.org/entity/Q107476723",
    "related__type": "uri",
    "relation": "instance of",
    "relation__type": "literal",
    "relatedLabel": "Q107476723",
    "relatedLabel__type": "literal"
  },
  {
    "seedLabel": "computer",
    "seedLabel__type": "literal",
    "seedLabel__lang": "en",
    "seed": "http://www.wikidata.org/entity/Q68",
    "seed__type": "uri",
    "related": "http://www.wikidata.org/entity/Q16796074",
    "related__type": "uri",
    "relation": "instance of",
    "relation__type": "literal",
    "relatedLabel": "Microserver",
    "relatedLabel__type": "literal",
    "relatedLabel__lang": "en"
  },
  {
    "seedLabel": "computer",
    "seedLabel__type": "literal",
    "seedLabel__lang": "en",
    "seed": "http://www.wikidata.org/entity/Q68",
    "seed__type": "uri",
    "related": "http://www.wikidata.org/entity/Q112679112",
    "related__type": "uri",
    "relation": "instance of",
    "relation__type": "literal",
    "relatedLabel": "Albert (computer)",
    "relatedLabel__type": "literal",
    "relatedLabel__lang": "en"
  },
  {
    "seedLabel": "computer",
    "seedLabel__type": "literal",
    "seedLabel__lang": "en",
    "seed": "http://www.wikidata.org/entity/Q68",
    "seed__type": "uri",
    "related": "http://www.wikidata.org/entity/Q116055567",
    "related__type": "uri",
    "relation": "instance of",
    "relation__type": "literal",
    "relatedLabel": "Intel NUC7CJYHN2",
    "relatedLabel__type": "literal",
    "relatedLabel__lang": "en"
  },
  {
    "seedLabel": "computer",
    "seedLabel__type": "literal",
    "seedLabel__lang": "en",
    "seed": "http://www.wikidata.org/entity/Q68",
    "seed__type": "uri",
    "related": "http://www.wikidata.org/entity/Q103821919",
    "related__type": "uri",
    "relation": "instance of",
    "relation__type": "literal",
    "relatedLabel": "Цзючжан",
    "relatedLabel__type": "literal",
    "relatedLabel__lang": "ru"
  },
  {
    "seedLabel": "computer",
    "seedLabel__type": "literal",
    "seedLabel__lang": "en",
    "seed": "http://www.wikidata.org/entity/Q68",
    "seed__type": "uri",
    "related": "http://www.wikidata.org/entity/Q134511378",
    "related__type": "uri",
    "relation": "instance of",
    "relation__type": "literal",
    "relatedLabel": "Q134511378",
    "relatedLabel__type": "literal"
  },
  {
    "seedLabel": "laptop",
    "seedLabel__type": "literal",
    "seedLabel__lang": "en",
    "seed": "http://www.wikidata.org/entity/Q3962",
    "seed__type": "uri",
    "related": "http://www.wikidata.org/entity/Q3738901",
    "related__type": "uri",
    "relation": "instance of",
    "relation__type": "literal",
    "relatedLabel": "PowerBook G3 Kanga",
    "relatedLabel__type": "literal",
    "relatedLabel__lang": "en"
  },
  {
    "seedLabel": "computer",
    "seedLabel__type": "literal",
    "seedLabel__lang": "en",
    "seed": "http://www.wikidata.org/entity/Q68",
    "seed__type": "uri",
    "related": "http://www.wikidata.org/entity/Q16909315",
    "related__type": "uri",
    "relation": "instance of",
    "relation__type": "literal",
    "relatedLabel": "NCR 304",
    "relatedLabel__type": "literal",
    "relatedLabel__lang": "en"
  },
  {
    "seedLabel": "computer",
    "seedLabel__type": "literal",
    "seedLabel__lang": "en",
    "seed": "http://www.wikidata.org/entity/Q68",
    "seed__type": "uri",
    "related": "http://www.wikidata.org/entity/Q125999984",
    "related__type": "uri",
    "relation": "instance of",
    "relation__type": "literal",
    "relatedLabel": "XIGMATEK Aquarius Plus",
    "relatedLabel__type": "literal",
    "relatedLabel__lang": "en"
  },
  {
    "seedLabel": "computer",
    "seedLabel__type": "literal",
    "seedLabel__lang": "en",
    "seed": "http://www.wikidata.org/entity/Q68",
    "seed__type": "uri",
    "related": "http://www.wikidata.org/entity/Q16980521",
    "related__type": "uri",
    "relation": "instance of",
    "relation__type": "literal",
    "relatedLabel": "FatPipe Networks",
    "relatedLabel__type": "literal",
    "relatedLabel__lang": "en"
  },
  {
    "seedLabel": "computer",
    "seedLabel__type": "literal",
    "seedLabel__lang": "en",
    "seed": "http://www.wikidata.org/entity/Q68",
    "seed__type": "uri",
    "related": "http://www.wikidata.org/entity/Q45358488",
    "related__type": "uri",
    "relation": "instance of",
    "relation__type": "literal",
    "relatedLabel": "Q45358488",
    "relatedLabel__type": "literal"
  },
  {
    "seedLabel": "computer",
    "seedLabel__type": "literal",
    "seedLabel__lang": "en",
    "seed": "http://www.wikidata.org/entity/Q68",
    "seed__type": "uri",
    "related": "http://www.wikidata.org/entity/Q130283505",
    "related__type": "uri",
    "relation": "instance of",
    "relation__type": "literal",
    "relatedLabel": "Q130283505",
    "relatedLabel__type": "literal"
  },
  {
    "seedLabel": "computer",
    "seedLabel__type": "literal",
    "seedLabel__lang": "en",
    "seed": "http://www.wikidata.org/entity/Q68",
    "seed__type": "uri",
    "related": "http://www.wikidata.org/entity/Q17016468",
    "related__type": "uri",
    "relation": "instance of",
    "relation__type": "literal",
    "relatedLabel": "IBM 4020 Military Computer",
    "relatedLabel__type": "literal",
    "relatedLabel__lang": "en"
  },
  {
    "seedLabel": "computer",
    "seedLabel__type": "literal",
    "seedLabel__lang": "en",
    "seed": "http://www.wikidata.org/entity/Q68",
    "seed__type": "uri",
    "related": "http://www.wikidata.org/entity/Q108045358",
    "related__type": "uri",
    "relation": "instance of",
    "relation__type": "literal",
    "relatedLabel": "Q108045358",
    "relatedLabel__type": "literal"
  },
  {
    "seedLabel": "laptop",
    "seedLabel__type": "literal",
    "seedLabel__lang": "en",
    "seed": "http://www.wikidata.org/entity/Q3962",
    "seed__type": "uri",
    "related": "http://www.wikidata.org/entity/Q477700",
    "related__type": "uri",
    "relation": "instance of",
    "relation__type": "literal",
    "relatedLabel": "Pedion",
    "relatedLabel__type": "literal",
    "relatedLabel__lang": "en"
  },
  {
    "seedLabel": "computer",
    "seedLabel__type": "literal",
    "seedLabel__lang": "en",
    "seed": "http://www.wikidata.org/entity/Q68",
    "seed__type": "uri",
    "related": "http://www.wikidata.org/entity/Q17081538",
    "related__type": "uri",
    "relation": "instance of",
    "relation__type": "literal",
    "relatedLabel": "Biological computer",
    "relatedLabel__type": "literal",
    "relatedLabel__lang": "en"
  },
  {
    "seedLabel": "computer",
    "seedLabel__type": "literal",
    "seedLabel__lang": "en",
    "seed": "http://www.wikidata.org/entity/Q68",
    "seed__type": "uri",
    "related": "http://www.wikidata.org/entity/Q17091767",
    "related__type": "uri",
    "relation": "instance of",
    "relation__type": "literal",
    "relatedLabel": "Next Unit of Computing",
    "relatedLabel__type": "literal",
    "relatedLabel__lang": "en"
  },
  {
    "seedLabel": "computer",
    "seedLabel__type": "literal",
    "seedLabel__lang": "en",
    "seed": "http://www.wikidata.org/entity/Q68",
    "seed__type": "uri",
    "related": "http://www.wikidata.org/entity/Q18752609",
    "related__type": "uri",
    "relation": "instance of",
    "relation__type": "literal",
    "relatedLabel": "Q18752609",
    "relatedLabel__type": "literal"
  },
  {
    "seedLabel": "computer",
    "seedLabel__type": "literal",
    "seedLabel__lang": "en",
    "seed": "http://www.wikidata.org/entity/Q68",
    "seed__type": "uri",
    "related": "http://www.wikidata.org/entity/Q30015097",
    "related__type": "uri",
    "relation": "instance of",
    "relation__type": "literal",
    "relatedLabel": "\"BeeZy\" BG-1000",
    "relatedLabel__type": "literal",
    "relatedLabel__lang": "en"
  },
  {
    "seedLabel": "computer",
    "seedLabel__type": "literal",
    "seedLabel__lang": "en",
    "seed": "http://www.wikidata.org/entity/Q68",
    "seed__type": "uri",
    "related": "http://www.wikidata.org/entity/Q30028602",
    "related__type": "uri",
    "relation": "instance of",
    "relation__type": "literal",
    "relatedLabel": "Logitech LG-10-Musée Bolo",
    "relatedLabel__type": "literal",
    "relatedLabel__lang": "en"
  },
  {
    "seedLabel": "laptop",
    "seedLabel__type": "literal",
    "seedLabel__lang": "en",
    "seed": "http://www.wikidata.org/entity/Q3962",
    "seed__type": "uri",
    "related": "http://www.wikidata.org/entity/Q1486822",
    "related__type": "uri",
    "relation": "instance of",
    "relation__type": "literal",
    "relatedLabel": "GRiD Compass",
    "relatedLabel__type": "literal",
    "relatedLabel__lang": "ru"
  },
  {
    "seedLabel": "computer",
    "seedLabel__type": "literal",
    "seedLabel__lang": "en",
    "seed": "http://www.wikidata.org/entity/Q68",
    "seed__type": "uri",
    "related": "http://www.wikidata.org/entity/Q59248259",
    "related__type": "uri",
    "relation": "instance of",
    "relation__type": "literal",
    "relatedLabel": "Q59248259",
    "relatedLabel__type": "literal"
  },
  {
    "seedLabel": "computer",
    "seedLabel__type": "literal",
    "seedLabel__lang": "en",
    "seed": "http://www.wikidata.org/entity/Q68",
    "seed__type": "uri",
    "related": "http://www.wikidata.org/entity/Q59248267",
    "related__type": "uri",
    "relation": "instance of",
    "relation__type": "literal",
    "relatedLabel": "Q59248267",
    "relatedLabel__type": "literal"
  },
  {
    "seedLabel": "computer",
    "seedLabel__type": "literal",
    "seedLabel__lang": "en",
    "seed": "http://www.wikidata.org/entity/Q68",
    "seed__type": "uri",
    "related": "http://www.wikidata.org/entity/Q113411819",
    "related__type": "uri",
    "relation": "instance of",
    "relation__type": "literal",
    "relatedLabel": "ЦИМ-1",
    "relatedLabel__type": "literal",
    "relatedLabel__lang": "ru"
  },
  {
    "seedLabel": "laptop",
    "seedLabel__type": "literal",
    "seedLabel__lang": "en",
    "seed": "http://www.wikidata.org/entity/Q3962",
    "seed__type": "uri",
    "related": "http://www.wikidata.org/entity/Q2413691",
    "related__type": "uri",
    "relation": "instance of",
    "relation__type": "literal",
    "relatedLabel": "PowerBook Duo 2300c",
    "relatedLabel__type": "literal",
    "relatedLabel__lang": "en"
  },
  {
    "seedLabel": "computer",
    "seedLabel__type": "literal",
    "seedLabel__lang": "en",
    "seed": "http://www.wikidata.org/entity/Q68",
    "seed__type": "uri",
    "related": "http://www.wikidata.org/entity/Q23828032",
    "related__type": "uri",
    "relation": "instance of",
    "relation__type": "literal",
    "relatedLabel": "CUB",
    "relatedLabel__type": "literal",
    "relatedLabel__lang": "en"
  },
  {
    "seedLabel": "computer",
    "seedLabel__type": "literal",
    "seedLabel__lang": "en",
    "seed": "http://www.wikidata.org/entity/Q68",
    "seed__type": "uri",
    "related": "http://www.wikidata.org/entity/Q135457378",
    "related__type": "uri",
    "relation": "instance of",
    "relation__type": "literal",
    "relatedLabel": "Q135457378",
    "relatedLabel__type": "literal"
  },
  {
    "seedLabel": "computer",
    "seedLabel__type": "literal",
    "seedLabel__lang": "en",
    "seed": "http://www.wikidata.org/entity/Q68",
    "seed__type": "uri",
    "related": "http://www.wikidata.org/entity/Q19841911",
    "related__type": "uri",
    "relation": "instance of",
    "relation__type": "literal",
    "relatedLabel": "LLC2",
    "relatedLabel__type": "literal",
    "relatedLabel__lang": "en"
  },
  {
    "seedLabel": "computer",
    "seedLabel__type": "literal",
    "seedLabel__lang": "en",
    "seed": "http://www.wikidata.org/entity/Q68",
    "seed__type": "uri",
    "related": "http://www.wikidata.org/entity/Q135525626",
    "related__type": "uri",
    "relation": "instance of",
    "relation__type": "literal",
    "relatedLabel": "Q135525626",
    "relatedLabel__type": "literal"
  },
  {
    "seedLabel": "computer",
    "seedLabel__type": "literal",
    "seedLabel__lang": "en",
    "seed": "http://www.wikidata.org/entity/Q68",
    "seed__type": "uri",
    "related": "http://www.wikidata.org/entity/Q24964906",
    "related__type": "uri",
    "relation": "instance of",
    "relation__type": "literal",
    "relatedLabel": "Hollerith Electronic Computer",
    "relatedLabel__type": "literal",
    "relatedLabel__lang": "en"
  },
  {
    "seedLabel": "computer",
    "seedLabel__type": "literal",
    "seedLabel__lang": "en",
    "seed": "http://www.wikidata.org/entity/Q68",
    "seed__type": "uri",
    "related": "http://www.wikidata.org/entity/Q134451419",
    "related__type": "uri",
    "relation": "instance of",
    "relation__type": "literal",
    "relatedLabel": "Telmac",
    "relatedLabel__type": "literal",
    "relatedLabel__lang": "en"
  },
  {
    "seedLabel": "computer",
    "seedLabel__type": "literal",
    "seedLabel__lang": "en",
    "seed": "http://www.wikidata.org/entity/Q68",
    "seed__type": "uri",
    "related": "http://www.wikidata.org/entity/Q24035766",
    "related__type": "uri",
    "relation": "instance of",
    "relation__type": "literal",
    "relatedLabel": "Q24035766",
    "relatedLabel__type": "literal"
  },
  {
    "seedLabel": "computer",
    "seedLabel__type": "literal",
    "seedLabel__lang": "en",
    "seed": "http://www.wikidata.org/entity/Q68",
    "seed__type": "uri",
    "related": "http://www.wikidata.org/entity/Q17561375",
    "related__type": "uri",
    "relation": "instance of",
    "relation__type": "literal",
    "relatedLabel": "TRASK",
    "relatedLabel__type": "literal",
    "relatedLabel__lang": "en"
  },
  {
    "seedLabel": "computer",
    "seedLabel__type": "literal",
    "seedLabel__lang": "en",
    "seed": "http://www.wikidata.org/entity/Q68",
    "seed__type": "uri",
    "related": "http://www.wikidata.org/entity/Q107298458",
    "related__type": "uri",
    "relation": "instance of",
    "relation__type": "literal",
    "relatedLabel": "IBM Leapfrog",
    "relatedLabel__type": "literal",
    "relatedLabel__lang": "en"
  },
  {
    "seedLabel": "computer",
    "seedLabel__type": "literal",
    "seedLabel__lang": "en",
    "seed": "http://www.wikidata.org/entity/Q68",
    "seed__type": "uri",
    "related": "http://www.wikidata.org/entity/Q28691839",
    "related__type": "uri",
    "relation": "instance of",
    "relation__type": "literal",
    "relatedLabel": "Q28691839",
    "relatedLabel__type": "literal"
  },
  {
    "seedLabel": "laptop",
    "seedLabel__type": "literal",
    "seedLabel__lang": "en",
    "seed": "http://www.wikidata.org/entity/Q3962",
    "seed__type": "uri",
    "related": "http://www.wikidata.org/entity/Q123537536",
    "related__type": "uri",
    "relation": "instance of",
    "relation__type": "literal",
    "relatedLabel": "Acer Aspire 4752",
    "relatedLabel__type": "literal",
    "relatedLabel__lang": "en"
  },
  {
    "seedLabel": "computer hardware",
    "seedLabel__type": "literal",
    "seedLabel__lang": "en",
    "seed": "http://www.wikidata.org/entity/Q3966",
    "seed__type": "uri",
    "related": "http://www.wikidata.org/entity/Q502600",
    "related__type": "uri",
    "relation": "instance of",
    "relation__type": "literal",
    "relatedLabel": "Amiga Chip RAM",
    "relatedLabel__type": "literal",
    "relatedLabel__lang": "en"
  },
  {
    "seedLabel": "laptop",
    "seedLabel__type": "literal",
    "seedLabel__lang": "en",
    "seed": "http://www.wikidata.org/entity/Q3962",
    "seed__type": "uri",
    "related": "http://www.wikidata.org/entity/Q11251028",
    "related__type": "uri",
    "relation": "instance of",
    "relation__type": "literal",
    "relatedLabel": "ThinkPad A series",
    "relatedLabel__type": "literal",
    "relatedLabel__lang": "en"
  },
  {
    "seedLabel": "laptop",
    "seedLabel__type": "literal",
    "seedLabel__lang": "en",
    "seed": "http://www.wikidata.org/entity/Q3962",
    "seed__type": "uri",
    "related": "http://www.wikidata.org/entity/Q11251922",
    "related__type": "uri",
    "relation": "instance of",
    "relation__type": "literal",
    "relatedLabel": "UL20A",
    "relatedLabel__type": "literal",
    "relatedLabel__lang": "en"
  },
  {
    "seedLabel": "laptop",
    "seedLabel__type": "literal",
    "seedLabel__lang": "en",
    "seed": "http://www.wikidata.org/entity/Q3962",
    "seed__type": "uri",
    "related": "http://www.wikidata.org/entity/Q93476932",
    "related__type": "uri",
    "relation": "instance of",
    "relation__type": "literal",
    "relatedLabel": "Surface Book 3",
    "relatedLabel__type": "literal",
    "relatedLabel__lang": "en"
  },
  {
    "seedLabel": "computer hardware",
    "seedLabel__type": "literal",
    "seedLabel__lang": "en",
    "seed": "http://www.wikidata.org/entity/Q3966",
    "seed__type": "uri",
    "related": "http://www.wikidata.org/entity/Q3097841",
    "related__type": "uri",
    "relation": "instance of",
    "relation__type": "literal",
    "relatedLabel": "доступность компьютера",
    "relatedLabel__type": "literal",
    "relatedLabel__lang": "ru"
  },
  {
    "seedLabel": "computer hardware",
    "seedLabel__type": "literal",
    "seedLabel__lang": "en",
    "seed": "http://www.wikidata.org/entity/Q3966",
    "seed__type": "uri",
    "related": "http://www.wikidata.org/entity/Q2495511",
    "related__type": "uri",
    "relation": "instance of",
    "relation__type": "literal",
    "relatedLabel": "Universal Audio Architecture",
    "relatedLabel__type": "literal",
    "relatedLabel__lang": "en"
  },
  {
    "seedLabel": "computer hardware",
    "seedLabel__type": "literal",
    "seedLabel__lang": "en",
    "seed": "http://www.wikidata.org/entity/Q3966",
    "seed__type": "uri",
    "related": "http://www.wikidata.org/entity/Q6964127",
    "related__type": "uri",
    "relation": "instance of",
    "relation__type": "literal",
    "relatedLabel": "Nanoroute",
    "relatedLabel__type": "literal",
    "relatedLabel__lang": "en"
  },
  {
    "seedLabel": "computer hardware",
    "seedLabel__type": "literal",
    "seedLabel__lang": "en",
    "seed": "http://www.wikidata.org/entity/Q3966",
    "seed__type": "uri",
    "related": "http://www.wikidata.org/entity/Q184736",
    "related__type": "uri",
    "relation": "instance of",
    "relation__type": "literal",
    "relatedLabel": "character generator",
    "relatedLabel__type": "literal",
    "relatedLabel__lang": "en"
  },
  {
    "seedLabel": "laptop",
    "seedLabel__type": "literal",
    "seedLabel__lang": "en",
    "seed": "http://www.wikidata.org/entity/Q3962",
    "seed__type": "uri",
    "related": "http://www.wikidata.org/entity/Q50283603",
    "related__type": "uri",
    "relation": "instance of",
    "relation__type": "literal",
    "relatedLabel": "MateBook X",
    "relatedLabel__type": "literal",
    "relatedLabel__lang": "en"
  },
  {
    "seedLabel": "laptop",
    "seedLabel__type": "literal",
    "seedLabel__lang": "en",
    "seed": "http://www.wikidata.org/entity/Q3962",
    "seed__type": "uri",
    "related": "http://www.wikidata.org/entity/Q104857229",
    "related__type": "uri",
    "relation": "instance of",
    "relation__type": "literal",
    "relatedLabel": "Compaq Armada",
    "relatedLabel__type": "literal",
    "relatedLabel__lang": "en"
  },
  {
    "seedLabel": "laptop",
    "seedLabel__type": "literal",
    "seedLabel__lang": "en",
    "seed": "http://www.wikidata.org/entity/Q3962",
    "seed__type": "uri",
    "related": "http://www.wikidata.org/entity/Q50347624",
    "related__type": "uri",
    "relation": "instance of",
    "relation__type": "literal",
    "relatedLabel": "HP Envy X2",
    "relatedLabel__type": "literal",
    "relatedLabel__lang": "en"
  },
  {
    "seedLabel": "computer hardware",
    "seedLabel__type": "literal",
    "seedLabel__lang": "en",
    "seed": "http://www.wikidata.org/entity/Q3966",
    "seed__type": "uri",
    "related": "http://www.wikidata.org/entity/Q4033611",
    "related__type": "uri",
    "relation": "instance of",
    "relation__type": "literal",
    "relatedLabel": "AirPort Express",
    "relatedLabel__type": "literal",
    "relatedLabel__lang": "ru"
  },
  {
    "seedLabel": "computer hardware",
    "seedLabel__type": "literal",
    "seedLabel__lang": "en",
    "seed": "http://www.wikidata.org/entity/Q3966",
    "seed__type": "uri",
    "related": "http://www.wikidata.org/entity/Q4039793",
    "related__type": "uri",
    "relation": "instance of",
    "relation__type": "literal",
    "relatedLabel": "HASP",
    "relatedLabel__type": "literal",
    "relatedLabel__lang": "ru"
  },
  {
    "seedLabel": "computer hardware",
    "seedLabel__type": "literal",
    "seedLabel__lang": "en",
    "seed": "http://www.wikidata.org/entity/Q3966",
    "seed__type": "uri",
    "related": "http://www.wikidata.org/entity/Q5153197",
    "related__type": "uri",
    "relation": "instance of",
    "relation__type": "literal",
    "relatedLabel": "Commodore 64 joystick adapters",
    "relatedLabel__type": "literal",
    "relatedLabel__lang": "en"
  },
  {
    "seedLabel": "computer hardware",
    "seedLabel__type": "literal",
    "seedLabel__lang": "en",
    "seed": "http://www.wikidata.org/entity/Q3966",
    "seed__type": "uri",
    "related": "http://www.wikidata.org/entity/Q5153200",
    "related__type": "uri",
    "relation": "instance of",
    "relation__type": "literal",
    "relatedLabel": "Commodore 64 peripherals",
    "relatedLabel__type": "literal",
    "relatedLabel__lang": "en"
  },
  {
    "seedLabel": "computer hardware",
    "seedLabel__type": "literal",
    "seedLabel__lang": "en",
    "seed": "http://www.wikidata.org/entity/Q3966",
    "seed__type": "uri",
    "related": "http://www.wikidata.org/entity/Q4053436",
    "related__type": "uri",
    "relation": "instance of",
    "relation__type": "literal",
    "relatedLabel": "Yamaha V9990",
    "relatedLabel__type": "literal",
    "relatedLabel__lang": "ru"
  },
  {
    "seedLabel": "computer hardware",
    "seedLabel__type": "literal",
    "seedLabel__lang": "en",
    "seed": "http://www.wikidata.org/entity/Q3966",
    "seed__type": "uri",
    "related": "http://www.wikidata.org/entity/Q7171593",
    "related__type": "uri",
    "relation": "instance of",
    "relation__type": "literal",
    "relatedLabel": "PetaBox",
    "relatedLabel__type": "literal",
    "relatedLabel__lang": "en"
  },
  {
    "seedLabel": "computer hardware",
    "seedLabel__type": "literal",
    "seedLabel__lang": "en",
    "seed": "http://www.wikidata.org/entity/Q3966",
    "seed__type": "uri",
    "related": "http://www.wikidata.org/entity/Q647840",
    "related__type": "uri",
    "relation": "instance of",
    "relation__type": "literal",
    "relatedLabel": "MagicJack",
    "relatedLabel__type": "literal",
    "relatedLabel__lang": "ru"
  },
  {
    "seedLabel": "computer hardware",
    "seedLabel__type": "literal",
    "seedLabel__lang": "en",
    "seed": "http://www.wikidata.org/entity/Q3966",
    "seed__type": "uri",
    "related": "http://www.wikidata.org/entity/Q649146",
    "related__type": "uri",
    "relation": "instance of",
    "relation__type": "literal",
    "relatedLabel": "IDE64",
    "relatedLabel__type": "literal",
    "relatedLabel__lang": "en"
  },
  {
    "seedLabel": "computer hardware",
    "seedLabel__type": "literal",
    "seedLabel__lang": "en",
    "seed": "http://www.wikidata.org/entity/Q3966",
    "seed__type": "uri",
    "related": "http://www.wikidata.org/entity/Q30913939",
    "related__type": "uri",
    "relation": "instance of",
    "relation__type": "literal",
    "relatedLabel": "KCS Power PC",
    "relatedLabel__type": "literal",
    "relatedLabel__lang": "en"
  },
  {
    "seedLabel": "computer hardware",
    "seedLabel__type": "literal",
    "seedLabel__lang": "en",
    "seed": "http://www.wikidata.org/entity/Q3966",
    "seed__type": "uri",
    "related": "http://www.wikidata.org/entity/Q175848",
    "related__type": "uri",
    "relation": "instance of",
    "relation__type": "literal",
    "relatedLabel": "microsequencer",
    "relatedLabel__type": "literal",
    "relatedLabel__lang": "en"
  },
  {
    "seedLabel": "computer hardware",
    "seedLabel__type": "literal",
    "seedLabel__lang": "en",
    "seed": "http://www.wikidata.org/entity/Q3966",
    "seed__type": "uri",
    "related": "http://www.wikidata.org/entity/Q7277804",
    "related__type": "uri",
    "relation": "instance of",
    "relation__type": "literal",
    "relatedLabel": "RT.X100",
    "relatedLabel__type": "literal",
    "relatedLabel__lang": "en"
  },
  {
    "seedLabel": "laptop",
    "seedLabel__type": "literal",
    "seedLabel__lang": "en",
    "seed": "http://www.wikidata.org/entity/Q3962",
    "seed__type": "uri",
    "related": "http://www.wikidata.org/entity/Q7392447",
    "related__type": "uri",
    "relation": "instance of",
    "relation__type": "literal",
    "relatedLabel": "SPARCbook",
    "relatedLabel__type": "literal",
    "relatedLabel__lang": "en"
  },
  {
    "seedLabel": "laptop",
    "seedLabel__type": "literal",
    "seedLabel__lang": "en",
    "seed": "http://www.wikidata.org/entity/Q3962",
    "seed__type": "uri",
    "related": "http://www.wikidata.org/entity/Q51954707",
    "related__type": "uri",
    "relation": "instance of",
    "relation__type": "literal",
    "relatedLabel": "Q51954707",
    "relatedLabel__type": "literal"
  },
  {
    "seedLabel": "computer hardware",
    "seedLabel__type": "literal",
    "seedLabel__lang": "en",
    "seed": "http://www.wikidata.org/entity/Q3966",
    "seed__type": "uri",
    "related": "http://www.wikidata.org/entity/Q7360331",
    "related__type": "uri",
    "relation": "instance of",
    "relation__type": "literal",
    "relatedLabel": "Roland MPU-IPC-T",
    "relatedLabel__type": "literal",
    "relatedLabel__lang": "en"
  },
  {
    "seedLabel": "laptop",
    "seedLabel__type": "literal",
    "seedLabel__lang": "en",
    "seed": "http://www.wikidata.org/entity/Q3962",
    "seed__type": "uri",
    "related": "http://www.wikidata.org/entity/Q123421859",
    "related__type": "uri",
    "relation": "instance of",
    "relation__type": "literal",
    "relatedLabel": "Walkabout",
    "relatedLabel__type": "literal",
    "relatedLabel__lang": "en"
  },
  {
    "seedLabel": "computer hardware",
    "seedLabel__type": "literal",
    "seedLabel__lang": "en",
    "seed": "http://www.wikidata.org/entity/Q3966",
    "seed__type": "uri",
    "related": "http://www.wikidata.org/entity/Q4036792",
    "related__type": "uri",
    "relation": "instance of",
    "relation__type": "literal",
    "relatedLabel": "CyberVision",
    "relatedLabel__type": "literal",
    "relatedLabel__lang": "ru"
  },
  {
    "seedLabel": "laptop",
    "seedLabel__type": "literal",
    "seedLabel__lang": "en",
    "seed": "http://www.wikidata.org/entity/Q3962",
    "seed__type": "uri",
    "related": "http://www.wikidata.org/entity/Q86318494",
    "related__type": "uri",
    "relation": "instance of",
    "relation__type": "literal",
    "relatedLabel": "ThinkPad X62",
    "relatedLabel__type": "literal",
    "relatedLabel__lang": "en"
  },
  {
    "seedLabel": "computer hardware",
    "seedLabel__type": "literal",
    "seedLabel__lang": "en",
    "seed": "http://www.wikidata.org/entity/Q3966",
    "seed__type": "uri",
    "related": "http://www.wikidata.org/entity/Q7418955",
    "related__type": "uri",
    "relation": "instance of",
    "relation__type": "literal",
    "relatedLabel": "Sansa Fuze",
    "relatedLabel__type": "literal",
    "relatedLabel__lang": "en"
  },
  {
    "seedLabel": "laptop",
    "seedLabel__type": "literal",
    "seedLabel__lang": "en",
    "seed": "http://www.wikidata.org/entity/Q3962",
    "seed__type": "uri",
    "related": "http://www.wikidata.org/entity/Q86347738",
    "related__type": "uri",
    "relation": "instance of",
    "relation__type": "literal",
    "relatedLabel": "ThinkPad X120e",
    "relatedLabel__type": "literal",
    "relatedLabel__lang": "en"
  },
  {
    "seedLabel": "laptop",
    "seedLabel__type": "literal",
    "seedLabel__lang": "en",
    "seed": "http://www.wikidata.org/entity/Q3962",
    "seed__type": "uri",
    "related": "http://www.wikidata.org/entity/Q86348037",
    "related__type": "uri",
    "relation": "instance of",
    "relation__type": "literal",
    "relatedLabel": "ThinkPad X200s",
    "relatedLabel__type": "literal",
    "relatedLabel__lang": "en"
  },
  {
    "seedLabel": "laptop",
    "seedLabel__type": "literal",
    "seedLabel__lang": "en",
    "seed": "http://www.wikidata.org/entity/Q3962",
    "seed__type": "uri",
    "related": "http://www.wikidata.org/entity/Q86348211",
    "related__type": "uri",
    "relation": "instance of",
    "relation__type": "literal",
    "relatedLabel": "ThinkPad X201i",
    "relatedLabel__type": "literal",
    "relatedLabel__lang": "en"
  },
  {
    "seedLabel": "laptop",
    "seedLabel__type": "literal",
    "seedLabel__lang": "en",
    "seed": "http://www.wikidata.org/entity/Q3962",
    "seed__type": "uri",
    "related": "http://www.wikidata.org/entity/Q86350829",
    "related__type": "uri",
    "relation": "instance of",
    "relation__type": "literal",
    "relatedLabel": "ThinkPad X61 Tablet",
    "relatedLabel__type": "literal",
    "relatedLabel__lang": "en"
  },
  {
    "seedLabel": "laptop",
    "seedLabel__type": "literal",
    "seedLabel__lang": "en",
    "seed": "http://www.wikidata.org/entity/Q3962",
    "seed__type": "uri",
    "related": "http://www.wikidata.org/entity/Q86351010",
    "related__type": "uri",
    "relation": "instance of",
    "relation__type": "literal",
    "relatedLabel": "ThinkPad X41 Tablet",
    "relatedLabel__type": "literal",
    "relatedLabel__lang": "en"
  },
  {
    "seedLabel": "laptop",
    "seedLabel__type": "literal",
    "seedLabel__lang": "en",
    "seed": "http://www.wikidata.org/entity/Q3962",
    "seed__type": "uri",
    "related": "http://www.wikidata.org/entity/Q86351210",
    "related__type": "uri",
    "relation": "instance of",
    "relation__type": "literal",
    "relatedLabel": "ThinkPad X220 Tablet",
    "relatedLabel__type": "literal",
    "relatedLabel__lang": "en"
  },
  {
    "seedLabel": "laptop",
    "seedLabel__type": "literal",
    "seedLabel__lang": "en",
    "seed": "http://www.wikidata.org/entity/Q3962",
    "seed__type": "uri",
    "related": "http://www.wikidata.org/entity/Q86351360",
    "related__type": "uri",
    "relation": "instance of",
    "relation__type": "literal",
    "relatedLabel": "ThinkPad X240",
    "relatedLabel__type": "literal",
    "relatedLabel__lang": "en"
  },
  {
    "seedLabel": "laptop",
    "seedLabel__type": "literal",
    "seedLabel__lang": "en",
    "seed": "http://www.wikidata.org/entity/Q3962",
    "seed__type": "uri",
    "related": "http://www.wikidata.org/entity/Q86351468",
    "related__type": "uri",
    "relation": "instance of",
    "relation__type": "literal",
    "relatedLabel": "ThinkPad X61",
    "relatedLabel__type": "literal",
    "relatedLabel__lang": "en"
  },
  {
    "seedLabel": "laptop",
    "seedLabel__type": "literal",
    "seedLabel__lang": "en",
    "seed": "http://www.wikidata.org/entity/Q3962",
    "seed__type": "uri",
    "related": "http://www.wikidata.org/entity/Q86358812",
    "related__type": "uri",
    "relation": "instance of",
    "relation__type": "literal",
    "relatedLabel": "ThinkPad X20",
    "relatedLabel__type": "literal",
    "relatedLabel__lang": "en"
  },
  {
    "seedLabel": "computer hardware",
    "seedLabel__type": "literal",
    "seedLabel__lang": "en",
    "seed": "http://www.wikidata.org/entity/Q3966",
    "seed__type": "uri",
    "related": "http://www.wikidata.org/entity/Q1340308",
    "related__type": "uri",
    "relation": "instance of",
    "relation__type": "literal",
    "relatedLabel": "unified threat management",
    "relatedLabel__type": "literal",
    "relatedLabel__lang": "ru"
  },
  {
    "seedLabel": "computer hardware",
    "seedLabel__type": "literal",
    "seedLabel__lang": "en",
    "seed": "http://www.wikidata.org/entity/Q3966",
    "seed__type": "uri",
    "related": "http://www.wikidata.org/entity/Q909109",
    "related__type": "uri",
    "relation": "instance of",
    "relation__type": "literal",
    "relatedLabel": "Sega System 16",
    "relatedLabel__type": "literal",
    "relatedLabel__lang": "ru"
  },
  {
    "seedLabel": "laptop",
    "seedLabel__type": "literal",
    "seedLabel__lang": "en",
    "seed": "http://www.wikidata.org/entity/Q3962",
    "seed__type": "uri",
    "related": "http://www.wikidata.org/entity/Q86373875",
    "related__type": "uri",
    "relation": "instance of",
    "relation__type": "literal",
    "relatedLabel": "ThinkPad X32",
    "relatedLabel__type": "literal",
    "relatedLabel__lang": "en"
  },
  {
    "seedLabel": "laptop",
    "seedLabel__type": "literal",
    "seedLabel__lang": "en",
    "seed": "http://www.wikidata.org/entity/Q3962",
    "seed__type": "uri",
    "related": "http://www.wikidata.org/entity/Q86374045",
    "related__type": "uri",
    "relation": "instance of",
    "relation__type": "literal",
    "relatedLabel": "ThinkPad X31",
    "relatedLabel__type": "literal",
    "relatedLabel__lang": "en"
  },
  {
    "seedLabel": "laptop",
    "seedLabel__type": "literal",
    "seedLabel__lang": "en",
    "seed": "http://www.wikidata.org/entity/Q3962",
    "seed__type": "uri",
    "related": "http://www.wikidata.org/entity/Q86374335",
    "related__type": "uri",
    "relation": "instance of",
    "relation__type": "literal",
    "relatedLabel": "ThinkPad X220",
    "relatedLabel__type": "literal",
    "relatedLabel__lang": "en"
  },
  {
    "seedLabel": "computer hardware",
    "seedLabel__type": "literal",
    "seedLabel__lang": "en",
    "seed": "http://www.wikidata.org/entity/Q3966",
    "seed__type": "uri",
    "related": "http://www.wikidata.org/entity/Q1129239",
    "related__type": "uri",
    "relation": "instance of",
    "relation__type": "literal",
    "relatedLabel": "контроллер",
    "relatedLabel__type": "literal",
    "relatedLabel__lang": "ru"
  },
  {
    "seedLabel": "computer hardware",
    "seedLabel__type": "literal",
    "seedLabel__lang": "en",
    "seed": "http://www.wikidata.org/entity/Q3966",
    "seed__type": "uri",
    "related": "http://www.wikidata.org/entity/Q668123",
    "related__type": "uri",
    "relation": "instance of",
    "relation__type": "literal",
    "relatedLabel": "Hard Rectangular Drive",
    "relatedLabel__type": "literal",
    "relatedLabel__lang": "en"
  },
  {
    "seedLabel": "computer hardware",
    "seedLabel__type": "literal",
    "seedLabel__lang": "en",
    "seed": "http://www.wikidata.org/entity/Q3966",
    "seed__type": "uri",
    "related": "http://www.wikidata.org/entity/Q5514651",
    "related__type": "uri",
    "relation": "instance of",
    "relation__type": "literal",
    "relatedLabel": "GScube",
    "relatedLabel__type": "literal",
    "relatedLabel__lang": "en"
  },
  {
    "seedLabel": "computer hardware",
    "seedLabel__type": "literal",
    "seedLabel__lang": "en",
    "seed": "http://www.wikidata.org/entity/Q3966",
    "seed__type": "uri",
    "related": "http://www.wikidata.org/entity/Q1135572",
    "related__type": "uri",
    "relation": "instance of",
    "relation__type": "literal",
    "relatedLabel": "таксометр",
    "relatedLabel__type": "literal",
    "relatedLabel__lang": "ru"
  },
  {
    "seedLabel": "laptop",
    "seedLabel__type": "literal",
    "seedLabel__lang": "en",
    "seed": "http://www.wikidata.org/entity/Q3962",
    "seed__type": "uri",
    "related": "http://www.wikidata.org/entity/Q111915601",
    "related__type": "uri",
    "relation": "instance of",
    "relation__type": "literal",
    "relatedLabel": "Tandy 1400LT",
    "relatedLabel__type": "literal",
    "relatedLabel__lang": "en"
  },
  {
    "seedLabel": "laptop",
    "seedLabel__type": "literal",
    "seedLabel__lang": "en",
    "seed": "http://www.wikidata.org/entity/Q3962",
    "seed__type": "uri",
    "related": "http://www.wikidata.org/entity/Q18515626",
    "related__type": "uri",
    "relation": "instance of",
    "relation__type": "literal",
    "relatedLabel": "Bobst Graphic Scrib Portable",
    "relatedLabel__type": "literal",
    "relatedLabel__lang": "en"
  }
]